preql/__init__.py
preql/__main__.py
preql/_base_imports.py
preql/api.py
preql/autocomplete.py
preql/base.py
preql/casts.py
preql/compiler.py
preql/core.pql
preql/evaluate.py
preql/exceptions.py
preql/interp_common.py
preql/interpreter.py
preql/jup_kernel/__init__.py
preql/jup_kernel/__main__.py
preql/jup_kernel/install.py
preql/jup_kernel/kernel.py
preql/loggers.py
preql/parser.py
preql/pql_ast.py
preql/pql_functions.py
preql/pql_objects.py
preql/pql_types.py
preql/preql.lark
preql/repl.py
preql/settings.py
preql/sql.py
preql/sql_interface.py
preql/types_impl.py
preql/utils.py
prequel-0.1.8.dist-info/entry_points.txt
prequel-0.1.8.dist-info/LICENSE
prequel-0.1.8.dist-info/WHEEL
prequel-0.1.8.dist-info/METADATA
prequel-0.1.8.dist-info/RECORD
