Metadata-Version: 2.1
Name: prequel
Version: 0.1.8
Summary: An interpreted relational query language that compiles to SQL
Home-page: https://github.com/erezsh/Preql
License: Interface-Protection Clause + MIT
Author: Erez Shin
Author-email: erezshin@gmail.com
Requires-Python: >=3.8,<4.0
Classifier: Intended Audience :: Developers
Classifier: License :: Other/Proprietary License
Classifier: Programming Language :: Python :: 3
Classifier: Programming Language :: Python :: 3.8
Classifier: Programming Language :: Python :: 3.9
Classifier: Topic :: Software Development :: Libraries :: Python Modules
Provides-Extra: mysql
Provides-Extra: pgsql
Requires-Dist: dsnparse
Requires-Dist: lark-parser (>=0.10.0,<0.11.0)
Requires-Dist: mysqlclient; extra == "mysql"
Requires-Dist: prompt-toolkit
Requires-Dist: psycopg2; extra == "pgsql"
Requires-Dist: pygments
Requires-Dist: rich
Requires-Dist: runtype (>=0.1.4,<0.2.0)
Requires-Dist: tqdm
Project-URL: Documentation, https://preql.readthedocs.io/en/latest/
Project-URL: Repository, https://github.com/erezsh/Preql
